framehints/__init__.py
framehints-1.0.1.dist-info/licenses/LICENSE.txt
framehints-1.0.1.dist-info/METADATA
framehints-1.0.1.dist-info/WHEEL
framehints-1.0.1.dist-info/top_level.txt
framehints-1.0.1.dist-info/RECORD
