Metadata-Version: 2.4
Name: framehints
Version: 1.0.1
Author-email: lutrarutra <lutrarutra@pm.me>
Requires-Python: >=3.11
License-File: LICENSE.txt
Requires-Dist: numpy>=2.2
Requires-Dist: interop>=1.5
Requires-Dist: pandas>=2.3
Dynamic: license-file
